yxutil/__init__.py
yxutil/config.py
yxutil/fileIO.py
yxutil/job.py
yxutil/os.py
yxutil/util.py
yxutil/versions.py
yxutil-0.0.5.dist-info/LICENSE
yxutil-0.0.5.dist-info/METADATA
yxutil-0.0.5.dist-info/WHEEL
yxutil-0.0.5.dist-info/top_level.txt
yxutil-0.0.5.dist-info/RECORD
