Metadata-Version: 2.1
Name: yxutil
Version: 0.0.5
Summary: Xu Yuxing's personal python tools.
Home-page: https://github.com/SouthernCD/yxutil
Author: Yuxing Xu
Author-email: xuyuxing@mail.kib.ac.cn
Requires-Python: >=3.5
License-File: LICENSE
Requires-Dist: numpy
Requires-Dist: pandas
Requires-Dist: tables
